lingmee/__init__.py
lingulio-1.59.0.dist-info/LICENSE
lingulio-1.59.0.dist-info/METADATA
lingulio-1.59.0.dist-info/WHEEL
lingulio-1.59.0.dist-info/top_level.txt
lingulio-1.59.0.dist-info/RECORD
